twisted/plugins/server.py
wokkel/__init__.py
wokkel/_version.py
wokkel/client.py
wokkel/compat.py
wokkel/component.py
wokkel/componentservertap.py
wokkel/data_form.py
wokkel/delay.py
wokkel/disco.py
wokkel/formats.py
wokkel/generic.py
wokkel/iwokkel.py
wokkel/muc.py
wokkel/ping.py
wokkel/pubsub.py
wokkel/server.py
wokkel/shim.py
wokkel/subprotocols.py
wokkel/xmppim.py
wokkel/test/__init__.py
wokkel/test/helpers.py
wokkel/test/test_client.py
wokkel/test/test_compat.py
wokkel/test/test_component.py
wokkel/test/test_data_form.py
wokkel/test/test_delay.py
wokkel/test/test_disco.py
wokkel/test/test_formats.py
wokkel/test/test_generic.py
wokkel/test/test_iwokkel.py
wokkel/test/test_muc.py
wokkel/test/test_ping.py
wokkel/test/test_pubsub.py
wokkel/test/test_server.py
wokkel/test/test_shim.py
wokkel/test/test_subprotocols.py
wokkel/test/test_version.py
wokkel/test/test_xmppim.py
wokkel-18.0.0.dist-info/LICENSE
wokkel-18.0.0.dist-info/METADATA
wokkel-18.0.0.dist-info/WHEEL
wokkel-18.0.0.dist-info/top_level.txt
wokkel-18.0.0.dist-info/RECORD
