Metadata-Version: 2.1
Name: wokkel
Version: 18.0.0
Summary: Twisted Jabber support library
Home-page: https://wokkel.ik.nu/
Author: Ralph Meijer
Author-email: ralphm@ik.nu
Maintainer-email: ralphm@ik.nu
License: MIT
Platform: any
Classifier: Programming Language :: Python :: 2.7
Classifier: Programming Language :: Python :: 3
Classifier: Programming Language :: Python :: 3.4
Classifier: Programming Language :: Python :: 3.5
Classifier: Programming Language :: Python :: 3.6
Requires-Dist: incremental (>=16.9.0)
Requires-Dist: python-dateutil
Requires-Dist: Twisted[tls] (>=15.5.0) ; python_version<'3'
Requires-Dist: Twisted[tls] (>=16.4.0) ; python_version>'3'
Provides-Extra: dev
Requires-Dist: pyflakes ; extra == 'dev'
Requires-Dist: coverage ; extra == 'dev'
Requires-Dist: sphinx ; extra == 'dev'
Requires-Dist: towncrier ; extra == 'dev'
Requires-Dist: pydoctor ; (python_version<'3') and extra == 'dev'
